{
  "timestamp": 82.813,
  "frame": 1963,
  "detections": [],
  "lane_state": {
    "lanes": [],
    "lane_center_offset_px": 0.0,
    "lane_confidence": 0.2,
    "num_tracked_lanes": 0,
    "ego_lane_width_px": null
  },
  "lane_info": {
    "num_lanes": 2,
    "current_lane": 2,
    "is_main_road": false,
    "lane_center_offset_px": 0.0,
    "lane_confidence": 0.2,
    "ego_lane_width_px": null,
    "num_tracked_lanes": 0
  },
  "decisions": {
    "brake": "none",
    "lane": "keep",
    "speed": "decrease",
    "risk": "high"
  },
  "alert_triggers": {
    "vehicle_ahead": false,
    "stop_sign": false,
    "red_traffic_light": false
  }
}